explainable_boosting_machine_pipeline/__init__.py
explainable_boosting_machine_pipeline/example_module.py
explainable_boosting_machine_pipeline/.ipynb_checkpoints/__init__-checkpoint.py
explainable_boosting_machine_pipeline/.ipynb_checkpoints/example_module-checkpoint.py
explainable_boosting_machine_pipeline-0.0.1.dist-info/METADATA
explainable_boosting_machine_pipeline-0.0.1.dist-info/WHEEL
explainable_boosting_machine_pipeline-0.0.1.dist-info/licenses/LICENSE
explainable_boosting_machine_pipeline-0.0.1.dist-info/RECORD
